setup.py
UsefulDB/__init__.py
UsefulDB/command_panel.py
UsefulDB/settings.py
UsefulDB.egg-info/PKG-INFO
UsefulDB.egg-info/SOURCES.txt
UsefulDB.egg-info/dependency_links.txt
UsefulDB.egg-info/requires.txt
UsefulDB.egg-info/top_level.txt
UsefulDB/Education/__init__.py