Metadata-Version: 1.0
Name: UsefulDB
Version: 1.0.5
Summary: Simplest utility for SQL-databases control
Home-page: http://github.com/ZerZru/UsefulDB
Author: Elisey Sharov
Author-email: elisei.sharow@yandex.ru
License: UNKNOWN
Platform: UNKNOWN
